monosi/__init__.py
monosi/scheduler/__init__.py
monosi/scheduler/base.py
monosi/scheduler/constants.py
monosi/scheduler/db.py
monosi/scheduler/job.py
monosi/scheduler/manager.py
monosi/scheduler/models/__init__.py
monosi/scheduler/models/audit_log.py
monosi/scheduler/models/execution.py
monosi/tasks/__init__.py
monosi/tasks/schedule.py
monosi_scheduler-0.0.1.dist-info/LICENSE
monosi_scheduler-0.0.1.dist-info/METADATA
monosi_scheduler-0.0.1.dist-info/WHEEL
monosi_scheduler-0.0.1.dist-info/top_level.txt
monosi_scheduler-0.0.1.dist-info/RECORD
