Metadata-Version: 2.1
Name: monosi-scheduler
Version: 0.0.1
Summary: Monosi Scheduler module
Home-page: UNKNOWN
Author: Vocable Inc
License: 
Platform: UNKNOWN
License-File: LICENSE
Requires-Dist: Flask-APScheduler (==1.12.2)
Requires-Dist: Flask-RESTful (==0.3.9)
Requires-Dist: Flask-SQLAlchemy (==2.5.1)
Requires-Dist: uuid (==1.30)
